{
    "status": 200,
    "message": "OK",
    "timestamp": "2025-11-26T17:20:42.7908664-03:00",
    "data": [
        {
            "code": "1520",
            "description": "Servicio de construcción de viviendas y comercial",
            "allowsTips": false
        },
        {
            "code": "1740",
            "description": "Albañilería, mampostería, colocación de azulejos, trabajos en yeso y aislamientos",
            "allowsTips": false
        },
        {
            "code": "1750",
            "description": "Carpinteros y otros servicios de carpintería",
            "allowsTips": false
        },
        {
            "code": "1771",
            "description": "Trabajos de hormigón y concreto",
            "allowsTips": false
        },
        {
            "code": "1799",
            "description": "Otros contratistas (no clasificados en otros rubros)",
            "allowsTips": false
        },
        {
            "code": "2741",
            "description": "Servicios editoriales, de publicación y de impresión varios",
            "allowsTips": false
        },
        {
            "code": "2842",
            "description": "Fabricantes de productos especiales de limpieza, pulido y saneamiento",
            "allowsTips": false
        },
        {
            "code": "4011",
            "description": "Servicio de fletes por vías ferroviarias",
            "allowsTips": false
        },
        {
            "code": "4111",
            "description": "Transporte de pasajeros local y suburbano",
            "allowsTips": false
        },
        {
            "code": "4112",
            "description": "Trenes y ferrocarriles de pasajeros",
            "allowsTips": false
        },
        {
            "code": "4214",
            "description": "Mudanzas, deliveries, servicos de mensajería o flete de corta y larga distancia",
            "allowsTips": false
        },
        {
            "code": "4215",
            "description": "Servicios de despachos postales aéreos y terrestres",
            "allowsTips": false
        },
        {
            "code": "4225",
            "description": "Proveedores de almacenamiento o depósito",
            "allowsTips": false
        },
        {
            "code": "4457",
            "description": "Alquiler y leasing de barcos y botes",
            "allowsTips": false
        },
        {
            "code": "4468",
            "description": "Marinas, guarderías y clubes náuticos",
            "allowsTips": false
        },
        {
            "code": "4511",
            "description": "Aerolíneas y compañías aéreas (no clasificados en otros rubros)",
            "allowsTips": false
        },
        {
            "code": "4582",
            "description": "Terminales aéreas: aeropuertos, aeródromos y pistas de aterrizaje",
            "allowsTips": false
        },
        {
            "code": "4722",
            "description": "Agencias de viaje y operadores turísticos",
            "allowsTips": false
        },
        {
            "code": "4784",
            "description": "Peajes y cánones de tránsito",
            "allowsTips": false
        },
        {
            "code": "4789",
            "description": "Servicios de transporte (no clasificados en otros rubros)",
            "allowsTips": false
        },
        {
            "code": "4812",
            "description": "Venta de equipos telefónicos y de telecomunicaciones",
            "allowsTips": false
        },
        {
            "code": "4814",
            "description": "Servicios de telecomunicaciones: locales, larga distancia y servicios de fax",
            "allowsTips": false
        },
        {
            "code": "4816",
            "description": "Proveedores de redes de computación e informatica",
            "allowsTips": false
        },
        {
            "code": "4829",
            "description": "Transferencia de dinero",
            "allowsTips": false
        },
        {
            "code": "4899",
            "description": "Servicios pagos de televisión, radio y streaming",
            "allowsTips": false
        },
        {
            "code": "4900",
            "description": "Servicios de electricidad, gas y agua",
            "allowsTips": false
        },
        {
            "code": "5013",
            "description": "Distribuidores y mayoristas de autopartes",
            "allowsTips": false
        },
        {
            "code": "5021",
            "description": "Distribuidores de amoblamiento comercial y de oficina",
            "allowsTips": false
        },
        {
            "code": "5039",
            "description": "Distribuidores de materiales de construcción (no clasificados en otros rubros)",
            "allowsTips": false
        },
        {
            "code": "5044",
            "description": "Distribuidores de suministros fotográficos y de fotocopiado",
            "allowsTips": false
        },
        {
            "code": "5045",
            "description": "Distribuidores de equipamiento de computación (software y hardware)",
            "allowsTips": false
        },
        {
            "code": "5046",
            "description": "Distribuidores de equipamiento comercial y suministros (no clasificados en otros rubros)",
            "allowsTips": false
        },
        {
            "code": "5047",
            "description": "Distribuidores de equipamiento medico, dental, oftálmico y suministros hospitalarios",
            "allowsTips": false
        },
        {
            "code": "5051",
            "description": "Metalúrgicas y distribuidores de productos metálicos",
            "allowsTips": false
        },
        {
            "code": "5065",
            "description": "Distribuidores de equipamiento y suministros eléctricos",
            "allowsTips": false
        },
        {
            "code": "5072",
            "description": "Distribuidores de artículos de ferretería",
            "allowsTips": false
        },
        {
            "code": "5074",
            "description": "Distribuidores de equipamiento y suministros de plomería y calefacción",
            "allowsTips": false
        },
        {
            "code": "5085",
            "description": "Distribuidores de suministros industriales (no clasificados en otros rubros)",
            "allowsTips": false
        },
        {
            "code": "5094",
            "description": "Distribuidores de relojes, joyas, piedras y metales preciosos",
            "allowsTips": false
        },
        {
            "code": "5111",
            "description": "Distribuidores de artículos de papelería, material de oficina, impresión y escritura",
            "allowsTips": false
        },
        {
            "code": "5122",
            "description": "Distribuidores de productos y suministros farmaceuticos",
            "allowsTips": false
        },
        {
            "code": "5131",
            "description": "Distribuidores de telas, mercerías y otros artículos por pieza",
            "allowsTips": false
        },
        {
            "code": "5137",
            "description": "Distribuidores de uniformes y ropa comercial",
            "allowsTips": false
        },
        {
            "code": "5139",
            "description": "Distribuidores de calzado comercial",
            "allowsTips": false
        },
        {
            "code": "5169",
            "description": "Distribuidores de insumos químicos y productos afines (no clasificados en otros rubros)",
            "allowsTips": false
        },
        {
            "code": "5172",
            "description": "Distribuidores de petróleo y productos derivados",
            "allowsTips": false
        },
        {
            "code": "5192",
            "description": "Distribuidores de libros, revistas y periódicos",
            "allowsTips": false
        },
        {
            "code": "5193",
            "description": "Distribuidores de suministros para floristerías y viveros",
            "allowsTips": false
        },
        {
            "code": "5198",
            "description": "Distribuidores de pinturas, barnices y suministros de pinturería",
            "allowsTips": false
        },
        {
            "code": "5199",
            "description": "Distribuidores de otros bienes no duraderos (no clasificados en otros rubros)",
            "allowsTips": false
        },
        {
            "code": "5200",
            "description": "Tiendas de artículos para el equipamiento del hogar",
            "allowsTips": false
        },
        {
            "code": "5211",
            "description": "Tiendas de madera y materiales de construcción",
            "allowsTips": false
        },
        {
            "code": "5231",
            "description": "Pinturerías y vidrierías",
            "allowsTips": false
        },
        {
            "code": "5251",
            "description": "Ferreterías",
            "allowsTips": false
        },
        {
            "code": "5261",
            "description": "Viveros y tiendas de jardín",
            "allowsTips": false
        },
        {
            "code": "5422",
            "description": "Frigoríficos, pescaderías, pollerías y otros alimentos congelados",
            "allowsTips": false
        },
        {
            "code": "5441",
            "description": "Chocolaterías, bombonerías y frutos secos",
            "allowsTips": false
        },
        {
            "code": "5451",
            "description": "Tiendas de productos lácteos",
            "allowsTips": false
        },
        {
            "code": "5511",
            "description": "Venta y reparación de vehículos",
            "allowsTips": false
        },
        {
            "code": "5521",
            "description": "Venta y reparación de vehículos usados",
            "allowsTips": false
        },
        {
            "code": "5532",
            "description": "Tiendas de neumáticos",
            "allowsTips": false
        },
        {
            "code": "5533",
            "description": "Tiendas de accesorios y repuestos para vehículos",
            "allowsTips": false
        },
        {
            "code": "5571",
            "description": "Venta de motocicletas",
            "allowsTips": false
        },
        {
            "code": "5599",
            "description": "Venta de equipamiento de automotores, aeronáuticos y agrícolas (no clasificados en otros rubros)",
            "allowsTips": false
        },
        {
            "code": "5611",
            "description": "Tiendas de indumentaria y accesorios para hombres y niños",
            "allowsTips": false
        },
        {
            "code": "5641",
            "description": "Tiendas de indumentaria infantil",
            "allowsTips": false
        },
        {
            "code": "5651",
            "description": "Tiendas de indumentaria general",
            "allowsTips": false
        },
        {
            "code": "5655",
            "description": "Tiendas de indumentaria deportiva",
            "allowsTips": false
        },
        {
            "code": "5661",
            "description": "Tiendas de calzado",
            "allowsTips": false
        },
        {
            "code": "5681",
            "description": "Tiendas de pieles y artículos de pieles",
            "allowsTips": false
        },
        {
            "code": "5699",
            "description": "Tiendas de indumentaria (no clasificados en otros rubros)",
            "allowsTips": false
        },
        {
            "code": "5712",
            "description": "Mueblerías y tiendas de equipamiento para el hogar",
            "allowsTips": false
        },
        {
            "code": "5713",
            "description": "Venta e instalación de pisos, baldosas y alfombras",
            "allowsTips": false
        },
        {
            "code": "5714",
            "description": "Tapicerías y tiendas de cortinas",
            "allowsTips": false
        },
        {
            "code": "5411",
            "description": "Supermercados y almacenes",
            "allowsTips": false
        },
        {
            "code": "5718",
            "description": "Tienda de chimeneas y accesorios para chimeneas",
            "allowsTips": false
        },
        {
            "code": "5719",
            "description": "Tiendas para el amoblamiento del hogar (no clasificados en otros rubros)",
            "allowsTips": false
        },
        {
            "code": "5732",
            "description": "Tiendas de electrónica y artículos para el hogar",
            "allowsTips": false
        },
        {
            "code": "5733",
            "description": "Tiendas de instrumentos musicales",
            "allowsTips": false
        },
        {
            "code": "5734",
            "description": "Tiendas de software de computación",
            "allowsTips": false
        },
        {
            "code": "5735",
            "description": "Disquerías",
            "allowsTips": false
        },
        {
            "code": "5818",
            "description": "Distribuidor de bienes digitales",
            "allowsTips": false
        },
        {
            "code": "5912",
            "description": "Farmacias y perfumerías",
            "allowsTips": false
        },
        {
            "code": "5921",
            "description": "Vinotecas, licorerías y tiendas de bebidas alcohólicas",
            "allowsTips": false
        },
        {
            "code": "5931",
            "description": "Venta de mercadería usada general",
            "allowsTips": false
        },
        {
            "code": "5932",
            "description": "Tiendas de antigüedades",
            "allowsTips": false
        },
        {
            "code": "5940",
            "description": "Venta y reparación de bicicletas",
            "allowsTips": false
        },
        {
            "code": "5941",
            "description": "Tiendas de artículos deportivos",
            "allowsTips": false
        },
        {
            "code": "5942",
            "description": "Librerías (tiendas de libros)",
            "allowsTips": false
        },
        {
            "code": "5943",
            "description": "Tiendas de artículos de papelería, material de oficina y útiles escolares",
            "allowsTips": false
        },
        {
            "code": "5944",
            "description": "Relojerías y joyerías",
            "allowsTips": false
        },
        {
            "code": "5945",
            "description": "Jugueterías y tiendas de juegos",
            "allowsTips": false
        },
        {
            "code": "5946",
            "description": "Tiendas de cámaras y artículos fotográficos",
            "allowsTips": false
        },
        {
            "code": "5948",
            "description": "Tiendas de equipaje y artículos de cuero",
            "allowsTips": false
        },
        {
            "code": "5949",
            "description": "Tiendas textiles y artículos de confección de indumentaria",
            "allowsTips": false
        },
        {
            "code": "5963",
            "description": "Ventas puerta a puerta",
            "allowsTips": false
        },
        {
            "code": "5964",
            "description": "Marketing directo - Ventas por catálogo",
            "allowsTips": false
        },
        {
            "code": "5966",
            "description": "Marketing directo - Telemarketing vía llamada saliente",
            "allowsTips": false
        },
        {
            "code": "5969",
            "description": "Marketing directo - Otras ventas (no clasificados en otros rubos)",
            "allowsTips": false
        },
        {
            "code": "5971",
            "description": "Galerías y venta de arte",
            "allowsTips": false
        },
        {
            "code": "5972",
            "description": "Filatelia y venta de monedas de colección",
            "allowsTips": false
        },
        {
            "code": "5977",
            "description": "Tiendas de cosméticos",
            "allowsTips": false
        },
        {
            "code": "5983",
            "description": "Venta de combustibles (no clasificados en otros rubos)",
            "allowsTips": false
        },
        {
            "code": "5992",
            "description": "Floristerías y viveros",
            "allowsTips": false
        },
        {
            "code": "5993",
            "description": "Tabaquerías",
            "allowsTips": false
        },
        {
            "code": "5994",
            "description": "Venta de díarios y revistas",
            "allowsTips": false
        },
        {
            "code": "5995",
            "description": "Tiendas de mascotas, alimentos y artículos para mascotas",
            "allowsTips": false
        },
        {
            "code": "5999",
            "description": "Tiendas de artículos especializados (no clasificados en otros rubos)",
            "allowsTips": false
        },
        {
            "code": "6211",
            "description": "Corredores de títulos financieros",
            "allowsTips": false
        },
        {
            "code": "6300",
            "description": "Compañias de seguros",
            "allowsTips": false
        },
        {
            "code": "6513",
            "description": "Agentes de bienes raíces y gestores inmobiliarios",
            "allowsTips": false
        },
        {
            "code": "7032",
            "description": "Instalaciones deportivas y recreativas",
            "allowsTips": false
        },
        {
            "code": "7216",
            "description": "Tintorerías",
            "allowsTips": false
        },
        {
            "code": "7221",
            "description": "Servicios de fotografía",
            "allowsTips": false
        },
        {
            "code": "7251",
            "description": "Reparación de calzado y zapaterías",
            "allowsTips": false
        },
        {
            "code": "7261",
            "description": "Servicios funebres y crematorios",
            "allowsTips": false
        },
        {
            "code": "7277",
            "description": "Servicios de asesoramiento financiero",
            "allowsTips": false
        },
        {
            "code": "7296",
            "description": "Alquiler de indumentaria",
            "allowsTips": false
        },
        {
            "code": "7299",
            "description": "Otros servicios personales (no clasificados en otros rubros)",
            "allowsTips": false
        },
        {
            "code": "7311",
            "description": "Agencias y servicios publicitarios",
            "allowsTips": false
        },
        {
            "code": "7321",
            "description": "Servicios de calificación crediticia",
            "allowsTips": false
        },
        {
            "code": "7333",
            "description": "Directores de arte, fotografía y diseñadores gráficos",
            "allowsTips": false
        },
        {
            "code": "7338",
            "description": "Servicios de copiado, planos y reproducciones",
            "allowsTips": false
        },
        {
            "code": "7342",
            "description": "Servicios de exterminio y desinfección",
            "allowsTips": false
        },
        {
            "code": "7349",
            "description": "Servicios de limpieza y mantenimiento",
            "allowsTips": false
        },
        {
            "code": "7361",
            "description": "Agencias de empleo y servicios temporales",
            "allowsTips": false
        },
        {
            "code": "7372",
            "description": "Servicios de programación, procesamiento y diseño de sistemas",
            "allowsTips": false
        },
        {
            "code": "7375",
            "description": "Servicios de recuperación de información",
            "allowsTips": false
        },
        {
            "code": "7379",
            "description": "Servicios de mantenimiento y reparación de computadoras (no clasificados en otros rubros)",
            "allowsTips": false
        },
        {
            "code": "7392",
            "description": "Servicios de gestión, consultoría y relacionistas públicos",
            "allowsTips": false
        },
        {
            "code": "7393",
            "description": "Servicios de protección, seguridad e investigación",
            "allowsTips": false
        },
        {
            "code": "7394",
            "description": "Alquiler y leasing de equipamientos, herramientas y muebles",
            "allowsTips": false
        },
        {
            "code": "7399",
            "description": "Otros servicios generales (no clasificados en otros rubros)",
            "allowsTips": false
        },
        {
            "code": "742",
            "description": "Servicios veterinarios",
            "allowsTips": false
        },
        {
            "code": "7512",
            "description": "Alquiler de automóviles",
            "allowsTips": false
        },
        {
            "code": "7513",
            "description": "Alquiler de trailers, camiones y utilitarios",
            "allowsTips": false
        },
        {
            "code": "7523",
            "description": "Estacionamientos, parquímetros y garajes",
            "allowsTips": false
        },
        {
            "code": "7534",
            "description": "Servicios de gomerías y reparación de neumáticos",
            "allowsTips": false
        },
        {
            "code": "7538",
            "description": "Otros talleres automotrices (no clasificados en otros rubros)",
            "allowsTips": false
        },
        {
            "code": "7542",
            "description": "Lavaderos de autos",
            "allowsTips": false
        },
        {
            "code": "7629",
            "description": "Talleres de reparaciónes eléctricas y de pequeños electrodomésticos",
            "allowsTips": false
        },
        {
            "code": "763",
            "description": "Cooperativas agrícolas",
            "allowsTips": false
        },
        {
            "code": "7631",
            "description": "Reparación de relojes y joyería",
            "allowsTips": false
        },
        {
            "code": "7641",
            "description": "Restauración de muebles, reparación y repintado",
            "allowsTips": false
        },
        {
            "code": "7699",
            "description": "Otros servicios de reparación (no clasificados en otros rubros)",
            "allowsTips": false
        },
        {
            "code": "780",
            "description": "Paisajismo y horticultura",
            "allowsTips": false
        },
        {
            "code": "7821",
            "description": "Producción y distribución de cine y video",
            "allowsTips": false
        },
        {
            "code": "7829",
            "description": "Producción y distribución de cine y video",
            "allowsTips": false
        },
        {
            "code": "7841",
            "description": "Videoclubes",
            "allowsTips": false
        },
        {
            "code": "7911",
            "description": "Estudios y escuelas de danza",
            "allowsTips": false
        },
        {
            "code": "7922",
            "description": "Productores teatrales y ticketeras",
            "allowsTips": false
        },
        {
            "code": "7932",
            "description": "Billares y pool",
            "allowsTips": false
        },
        {
            "code": "7941",
            "description": "Clubes y campos deportivos",
            "allowsTips": false
        },
        {
            "code": "6010",
            "description": "Desembolso de efectivo - Bancos e instituciones financieras",
            "allowsTips": false
        },
        {
            "code": "6012",
            "description": "Proveedores de servicios financieros (solo entidades financieras)",
            "allowsTips": false
        },
        {
            "code": "6051",
            "description": "Casas de cambio y otros servicios financieros por entidades no financieras",
            "allowsTips": false
        },
        {
            "code": "7991",
            "description": "Atracciones turísticas y exhibiciones",
            "allowsTips": false
        },
        {
            "code": "7995",
            "description": "Casinos, loterías y juegos de azar",
            "allowsTips": false
        },
        {
            "code": "7996",
            "description": "Parques de diversiones y circos",
            "allowsTips": false
        },
        {
            "code": "7997",
            "description": "Membresías de clubes sociales, recreacionales y deportivos",
            "allowsTips": false
        },
        {
            "code": "7998",
            "description": "Acuarios y zoológicos",
            "allowsTips": false
        },
        {
            "code": "7999",
            "description": "Servicios de recreación (no clasificados en otros rubros)",
            "allowsTips": false
        },
        {
            "code": "8011",
            "description": "Médicos (no clasificados en otros rubros)",
            "allowsTips": false
        },
        {
            "code": "8021",
            "description": "Dentistas y ortodoncistas",
            "allowsTips": false
        },
        {
            "code": "8031",
            "description": "Osteópatas",
            "allowsTips": false
        },
        {
            "code": "8043",
            "description": "Opticas",
            "allowsTips": false
        },
        {
            "code": "8050",
            "description": "Servicios de cuidado personal, geriátricos",
            "allowsTips": false
        },
        {
            "code": "8071",
            "description": "Laboratorios médicos y dentales",
            "allowsTips": false
        },
        {
            "code": "8099",
            "description": "Otros servicios médicos y de salud (no clasificados en otros rubros)",
            "allowsTips": false
        },
        {
            "code": "8211",
            "description": "Escuelas primarias y secundarias",
            "allowsTips": false
        },
        {
            "code": "8220",
            "description": "Universidades y colegios profesionales",
            "allowsTips": false
        },
        {
            "code": "8249",
            "description": "Escuelas de oficios y servicios vocacionales",
            "allowsTips": false
        },
        {
            "code": "8299",
            "description": "Otros servicios educativos (no clasificados en otros rubros)",
            "allowsTips": false
        },
        {
            "code": "8351",
            "description": "Servicios de cuidado infantil",
            "allowsTips": false
        },
        {
            "code": "8398",
            "description": "Organizaciones de caridad y servicio social",
            "allowsTips": false
        },
        {
            "code": "8641",
            "description": "Asociaciones sociales civiles",
            "allowsTips": false
        },
        {
            "code": "8651",
            "description": "Organizaciones políticas",
            "allowsTips": false
        },
        {
            "code": "8661",
            "description": "Organizaciones religiosas",
            "allowsTips": false
        },
        {
            "code": "8699",
            "description": "Otras organizaciones de membresía (no clasificados en otros rubros)",
            "allowsTips": false
        },
        {
            "code": "8734",
            "description": "Laboratorios de pruebas no médicas",
            "allowsTips": false
        },
        {
            "code": "8911",
            "description": "Servicios de arquitectura, ingeniería y agrimensura",
            "allowsTips": false
        },
        {
            "code": "8931",
            "description": "Servicios de contabilidad y auditoría",
            "allowsTips": false
        },
        {
            "code": "8999",
            "description": "Otros servicios profesionales (no clasificados en otros rubros)",
            "allowsTips": false
        },
        {
            "code": "9311",
            "description": "Pago de impuestos, rentas y tasas",
            "allowsTips": false
        },
        {
            "code": "9399",
            "description": "Otros servicios gubernamentales (no clasificados en otros rubros)",
            "allowsTips": false
        },
        {
            "code": "4121",
            "description": "Taxis, limosinas y servcio de transporte particular de pasajeros",
            "allowsTips": true
        },
        {
            "code": "5462",
            "description": "Panaderías",
            "allowsTips": true
        },
        {
            "code": "5499",
            "description": "Tiendas de alimentos preparados (no clasificados en otros rubros)",
            "allowsTips": true
        },
        {
            "code": "5811",
            "description": "Catering y preparación de alimentos para eventos",
            "allowsTips": true
        },
        {
            "code": "5812",
            "description": "Restaurantes",
            "allowsTips": true
        },
        {
            "code": "5813",
            "description": "Bares, boliches y discotecas",
            "allowsTips": true
        },
        {
            "code": "5814",
            "description": "Restaurantes de comida rápida y fast food",
            "allowsTips": true
        },
        {
            "code": "7011",
            "description": "Hoteles, y otros servicios de alojamiento (no clasificados en otros rubros)",
            "allowsTips": true
        },
        {
            "code": "7230",
            "description": "Peluquerías y barberías",
            "allowsTips": true
        },
        {
            "code": "7298",
            "description": "Spas y centros de belleza",
            "allowsTips": true
        },
        {
            "code": "5541",
            "description": "Venta de combustible en estaciones de servicio",
            "allowsTips": true
        }
    ],
    "errors": []
}